labgen.py
lablegen.py
lablegen-0.2.1.data/scripts/labgen.py
lablegen-0.2.1.data/scripts/lablegen.py
lablegen-0.2.1.dist-info/COPYING
lablegen-0.2.1.dist-info/METADATA
lablegen-0.2.1.dist-info/WHEEL
lablegen-0.2.1.dist-info/top_level.txt
lablegen-0.2.1.dist-info/RECORD
