Metadata-Version: 2.1
Name: lablegen
Version: 0.2.1
Summary: Generate LaTeX format table from array data.
Home-page: https://github.com/Social-Mean/LableGen
Author: Social Mean
Author-email: Social_Mean@126.com
License: GNU 3.0
Classifier: Programming Language :: Python :: 3
Classifier: License :: OSI Approved :: GNU Affero General Public License v3
Classifier: Operating System :: OS Independent
License-File: COPYING
Requires-Dist: pyperclip
Requires-Dist: numpy
